sappgen/__init__.py
sappgen/sappgen.py
sappgen/cfg/__init__.py
sappgen/cfg/config.py
sappgen/template_files/template1/project/Makefile.template
sappgen/template_files/template1/project/README.md.template
sappgen/template_files/template1/project/config.ini.template
sappgen/template_files/template1/project/main.py.template
sappgen/template_files/template1/project/requirements-dev.txt.template
sappgen/template_files/template1/project/testapp/__init__.py.template
sappgen/template_files/template1/project/testapp/app.py.template
sappgen/template_files/template1/project/testapp/util/__init__.py.template
sappgen/template_files/template1/project/testapp/util/log_util.py.template
sappgen/template_files/template1/project/tests/test_testapp.py.template
sappgen/template_files/template2/project/Makefile.template
sappgen/template_files/template2/project/README.md.template
sappgen/template_files/template2/project/config.ini.template
sappgen/template_files/template2/project/requirements.txt.template
sappgen/template_files/template2/project/testapp/__init__.py.template
sappgen/template_files/template2/project/testapp/main.py.template
sappgen/template_files/template2/project/testapp/routes/__init__.py.template
sappgen/template_files/template2/project/testapp/routes/test_routes.py.template
sappgen/template_files/template2/project/testapp/util/__init__.py.template
sappgen/template_files/template2/project/testapp/util/log_util.py.template
sappgen/template_files/template2/project/tests/test_main.py.template
sappgen/templates/__init__.py
sappgen/templates/template1.py
sappgen/templates/template2.py
sappgen/util/__init__.py
sappgen/util/file_util.py
sappgen/util/log_util.py
sappgen-1.0.8.dist-info/METADATA
sappgen-1.0.8.dist-info/RECORD
sappgen-1.0.8.dist-info/WHEEL
sappgen-1.0.8.dist-info/entry_points.txt
sappgen-1.0.8.dist-info/top_level.txt
