Metadata-Version: 2.1
Name: sappgen
Version: 1.0.8
Summary: Simple App Generator - Python
Home-page: https://github.com/aayushuppal/sappgen
Author: Aayush Uppal
Author-email: aayuppal@gmail.com
License: MIT
Platform: UNKNOWN
Classifier: License :: OSI Approved :: MIT License
Classifier: Programming Language :: Python
Classifier: Programming Language :: Python :: 3
